<?xml version="1.0" encoding="UTF-8" standalone="no"?>
<photos monument="Basilica di San Zeno">

<photo  date_taken="2007-08-04 18:15:23" description="Uno dei leoni davanti al portale di San Zeno Maggiore." id="2211953000" latitude="45.442578" license="3" longitude="10.979118" nbComments="5" rank="1" tags="verona veneto italia italy europa europe chiesa church basilica sanzenomaggiore leone" title="Verona" url_b="http://static.flickr.com/2032/2211953000_0caa875c3d_b.jpg" username="trinchetto" views="219" />
<photo  date_taken="2007-08-04 18:17:30" description="" id="2211952034" latitude="45.442578" license="3" longitude="10.979118" nbComments="5" rank="2" tags="verona veneto italia italy europa europe chiostro romanico chiesa church basilica sanzenomaggiore" title="Verona, Chiostro di San Zeno Maggiore" url_b="http://static.flickr.com/2417/2211952034_00e8513f4a_b.jpg" username="trinchetto" views="257" />
<photo  date_taken="2007-08-04 18:14:18" description="La Basilica di San Zeno Maggiore è giustamente considerata una delle massime glorie dell'architettura romanica. L'edificio attuale corrisponde alla terza ricostruzione della Basilica (si ha notizia, infatti, di altre due precedenti chiese, del IV-V sec. e del IX), risalente a circa il 1120. A breve distanza da questa data iniziarono gli ampliamenti, durati fino a tutto il sec. XIV e conclusi col rifacimento gotico del soffitto e dell'abside. La stupenda facciata - forse la più armonica e perfetta di quest'epoca - sorge al limite di una grande piazza lastricata, ed ha ai lati il bellissimo Campanile romanico della prima metà del sec. XII, modello insuperato nel genere, e la rossa Torre duecentesca dell'antica Abbazia (di quest'ultima fa menzione Dante nel c. XVIII del Purgatorio). Fulcro compositivo di questa architettura la grande e mirabile finestra circolare raggiata, con rilievi del M.Brioloto con i simboli della fortuna umana: a questo artista, noto fra il 1189 e il 1220, si tende oggi ad attribuire oltre a quello della &amp;quot;ruota&amp;quot;, il serrato disegno dell'intera facciata. Sulle cornici degli spioventi fregi figurati di Adamino da San Giorgio (primi del sec. XIII). Fonte: &lt;a href=&quot;http://www.fieradiverona.it/verona/sanzeno_page.htm&quot; rel=&quot;nofollow&quot;&gt;www.fieradiverona.it/verona/sanzeno_page.htm&lt;/a&gt;" id="2211980972" latitude="45.442578" license="3" longitude="10.979118" nbComments="38" rank="3" tags="verona veneto italia italy europa europe chiesa church basilica sanzenomaggiore romanico italiamedievale" title="Verona, San Zeno Maggiore" url_b="http://static.flickr.com/2188/2211980972_26f5125971_b.jpg" username="trinchetto" views="1836" />
<photo  date_taken="2010-02-13 17:43:33" description="Basilica di San Zeno a Verona" id="4355327089" latitude="45.44265" license="4" longitude="10.979257" nbComments="1" rank="4" tags="verona basilicadisanzeno sanzeno basilica" title="Basilica di San Zeno" url_b="http://static.flickr.com/4010/4355327089_c66a9400ae_b.jpg" username="br1dotcom" views="150" />
<photo  date_taken="2010-02-13 17:40:51" description="Basilica di San Zeno a Verona" id="4356059458" latitude="45.44265" license="4" longitude="10.979257" nbComments="2" rank="5" tags="verona basilicadisanzeno sanzeno basilica" title="Basilica di San Zeno" url_b="http://static.flickr.com/4042/4356059458_30dc0a8cee_b.jpg" username="br1dotcom" views="215" />
<photo  date_taken="2010-02-13 17:38:05" description="Basilica di San Zeno a Verona" id="4355304089" latitude="45.44265" license="4" longitude="10.979257" nbComments="1" rank="6" tags="verona basilicadisanzeno sanzeno basilica" title="Basilica di San Zeno" url_b="http://static.flickr.com/4035/4355304089_f3ac65a4b9_b.jpg" username="br1dotcom" views="554" />
<photo  date_taken="2010-02-13 17:35:51" description="Basilica di San Zeno a Verona" id="4356036922" latitude="45.44265" license="4" longitude="10.979257" nbComments="1" rank="7" tags="verona basilicadisanzeno sanzeno basilica" title="Basilica di San Zeno" url_b="http://static.flickr.com/4016/4356036922_074872e899_b.jpg" username="br1dotcom" views="120" />
<photo  date_taken="2010-02-13 17:42:46" description="Basilica di San Zeno a Verona" id="4355321825" latitude="45.44265" license="4" longitude="10.979257" nbComments="1" rank="8" tags="verona basilicadisanzeno sanzeno basilica" title="Basilica di San Zeno" url_b="http://static.flickr.com/2677/4355321825_f3ab613031_b.jpg" username="br1dotcom" views="120" />
<photo  date_taken="2010-02-13 17:37:07" description="Basilica di San Zeno a Verona" id="4356040626" latitude="45.44265" license="4" longitude="10.979257" nbComments="1" rank="9" tags="verona basilicadisanzeno sanzeno basilica" title="Basilica di San Zeno" url_b="http://static.flickr.com/2740/4356040626_8727e69209_b.jpg" username="br1dotcom" views="137" />
<photo  date_taken="2010-02-13 17:38:53" description="Basilica di San Zeno a Verona" id="4355308569" latitude="45.44265" license="4" longitude="10.979257" nbComments="1" rank="10" tags="verona basilicadisanzeno sanzeno basilica" title="Basilica di San Zeno" url_b="http://static.flickr.com/2753/4355308569_a6d4d0ae51_b.jpg" username="br1dotcom" views="160" />
<photo  date_taken="2010-02-13 17:43:28" description="Basilica di San Zeno a Verona" id="4356068076" latitude="45.44265" license="4" longitude="10.979257" nbComments="1" rank="11" tags="verona basilicadisanzeno sanzeno basilica" title="Basilica di San Zeno" url_b="http://static.flickr.com/4018/4356068076_47000e799e_b.jpg" username="br1dotcom" views="147" />
<photo  date_taken="2010-02-13 17:45:08" description="Basilica di San Zeno a Verona" id="4356076700" latitude="45.44265" license="4" longitude="10.979257" nbComments="1" rank="12" tags="verona basilicadisanzeno sanzeno basilica" title="Basilica di San Zeno" url_b="http://static.flickr.com/4006/4356076700_ed81c7032f_b.jpg" username="br1dotcom" views="115" />
<photo  date_taken="2010-02-13 17:37:10" description="Basilica di San Zeno a Verona" id="4356042812" latitude="45.44265" license="4" longitude="10.979257" nbComments="1" rank="13" tags="verona basilicadisanzeno sanzeno basilica" title="Basilica di San Zeno" url_b="http://static.flickr.com/4004/4356042812_f7a8bbc783_b.jpg" username="br1dotcom" views="242" />
<photo  date_taken="2010-02-13 17:44:17" description="Basilica di San Zeno a Verona" id="4356071478" latitude="45.44265" license="4" longitude="10.979257" nbComments="2" rank="14" tags="verona basilicadisanzeno sanzeno basilica" title="Basilica di San Zeno" url_b="http://static.flickr.com/4016/4356071478_3540348f76_b.jpg" username="br1dotcom" views="106" />
<photo  date_taken="2010-02-13 17:44:21" description="Basilica di San Zeno a Verona" id="4356072948" latitude="45.44265" license="4" longitude="10.979257" nbComments="1" rank="15" tags="verona basilicadisanzeno sanzeno basilica" title="Basilica di San Zeno" url_b="http://static.flickr.com/4005/4356072948_09354d985f_b.jpg" username="br1dotcom" views="104" />
<photo  date_taken="2010-02-13 17:45:11" description="Basilica di San Zeno a Verona" id="4355335667" latitude="45.44265" license="4" longitude="10.979257" nbComments="1" rank="16" tags="verona basilicadisanzeno sanzeno basilica" title="Basilica di San Zeno" url_b="http://static.flickr.com/2702/4355335667_a8e56b48d1_b.jpg" username="br1dotcom" views="62" />
<photo  date_taken="2010-02-13 17:41:15" description="Basilica di San Zeno a Verona" id="4355320193" latitude="45.44265" license="4" longitude="10.979257" nbComments="1" rank="17" tags="verona basilicadisanzeno sanzeno basilica" title="Basilica di San Zeno" url_b="http://static.flickr.com/4034/4355320193_5d134b16c8_b.jpg" username="br1dotcom" views="334" />
<photo  date_taken="2010-02-13 17:38:15" description="Basilica di San Zeno a Verona" id="4356049088" latitude="45.44265" license="4" longitude="10.979257" nbComments="1" rank="18" tags="verona basilicadisanzeno sanzeno basilica" title="Basilica di San Zeno" url_b="http://static.flickr.com/4047/4356049088_859b815c78_b.jpg" username="br1dotcom" views="222" />
<photo  date_taken="2010-02-13 17:36:16" description="Basilica di San Zeno a Verona" id="4356038724" latitude="45.44265" license="4" longitude="10.979257" nbComments="1" rank="19" tags="verona basilicadisanzeno sanzeno basilica" title="Basilica di San Zeno" url_b="http://static.flickr.com/4069/4356038724_3145fc211e_b.jpg" username="br1dotcom" views="429" />
<photo  date_taken="2010-02-13 17:44:41" description="Basilica di San Zeno a Verona" id="4355332119" latitude="45.44265" license="4" longitude="10.979257" nbComments="1" rank="20" tags="verona basilicadisanzeno sanzeno basilica" title="Basilica di San Zeno" url_b="http://static.flickr.com/2744/4355332119_87ddffce1e_b.jpg" username="br1dotcom" views="108" />
<photo  date_taken="2010-02-13 17:39:20" description="Basilica di San Zeno a Verona" id="4356053804" latitude="45.44265" license="4" longitude="10.979257" nbComments="1" rank="21" tags="verona basilicadisanzeno sanzeno basilica" title="Basilica di San Zeno" url_b="http://static.flickr.com/2738/4356053804_4a370b1ff2_b.jpg" username="br1dotcom" views="156" />
<photo  date_taken="2010-02-13 17:37:47" description="Basilica di San Zeno a Verona" id="4355302241" latitude="45.44265" license="4" longitude="10.979257" nbComments="1" rank="22" tags="verona basilicadisanzeno sanzeno basilica" title="Basilica di San Zeno" url_b="http://static.flickr.com/4049/4355302241_9b878b9b99_b.jpg" username="br1dotcom" views="160" />
<photo  date_taken="2010-07-30 13:28:27" description="" id="5134922301" latitude="45.442499" license="5" longitude="10.978833" nbComments="0" rank="23" tags="architecture basilicadisanzeno church cloister day italy verona vvv2010" title="Cloister of Basilica di San Zeno" url_b="http://static.flickr.com/4026/5134922301_5804c5bba6_b.jpg" username="jiuguangw" views="112" />
<photo  date_taken="2010-02-13 17:33:44" description="Basilica di San Zeno a Verona" id="4356032534" latitude="45.442925" license="4" longitude="10.979118" nbComments="1" rank="24" tags="verona basilicadisanzeno sanzeno basilica" title="Basilica di San Zeno" url_b="http://static.flickr.com/4052/4356032534_67957ea6b7_b.jpg" username="br1dotcom" views="56" />
<photo  date_taken="2010-02-13 17:32:28" description="Basilica di San Zeno a Verona" id="4356031170" latitude="45.442925" license="4" longitude="10.979118" nbComments="1" rank="25" tags="verona basilicadisanzeno sanzeno basilica" title="Basilica di San Zeno" url_b="http://static.flickr.com/2729/4356031170_aa057f715f_b.jpg" username="br1dotcom" views="73" />
<photo  date_taken="2010-02-13 17:33:57" description="Basilica di San Zeno a Verona" id="4356033766" latitude="45.442925" license="4" longitude="10.979118" nbComments="1" rank="26" tags="verona basilicadisanzeno sanzeno basilica" title="Basilica di San Zeno" url_b="http://static.flickr.com/2691/4356033766_a09cd92350_b.jpg" username="br1dotcom" views="39" />
<photo  date_taken="2010-02-13 17:30:46" description="Basilica di San Zeno a Verona" id="4356028126" latitude="45.442722" license="4" longitude="10.978549" nbComments="1" rank="27" tags="verona basilicadisanzeno sanzeno basilica" title="Basilica di San Zeno" url_b="http://static.flickr.com/4016/4356028126_5bbef2eb09_b.jpg" username="br1dotcom" views="28" />
<photo  date_taken="2009-07-24 17:38:20" description="" id="3755367835" latitude="45.442501" license="5" longitude="10.979167" nbComments="0" rank="28" tags="basilicadisanzeno sanzeno verona church" title="Basilica di San Zeno" url_b="http://static.flickr.com/2510/3755367835_08530ffafd_b.jpg" username="Andrew Dupont" views="70" />
<photo  date_taken="2009-07-24 17:31:49" description="" id="3755362717" latitude="45.442501" license="5" longitude="10.979167" nbComments="0" rank="29" tags="basilicadisanzeno sanzeno verona church" title="Basilica di San Zeno" url_b="http://static.flickr.com/3447/3755362717_64c4a4efaf_b.jpg" username="Andrew Dupont" views="112" />
<photo  date_taken="1995-01-01 00:00:00" description="" id="5336951122" latitude="45.442571" license="4" longitude="10.979225" nbComments="0" rank="30" tags="1995 veneto architectuur kerk verona europa italië" title="Basilica di San Zeno - Verona {1995}" url_b="http://static.flickr.com/5123/5336951122_0daa15f47c_b.jpg" username="westher" views="44" />
<photo  date_taken="2007-08-04 18:15:33" description="Uno dei leoni davanti al portale di San Zeno Maggiore." id="2211161073" latitude="45.442578" license="3" longitude="10.979118" nbComments="4" rank="31" tags="verona veneto italia italy europa europe chiesa church leone sanzenomaggiore basilica" title="Verona" url_b="http://static.flickr.com/2328/2211161073_1ddaea55af_b.jpg" username="trinchetto" views="187" />
<photo  date_taken="2011-06-01 16:24:56" description="Basilica di San Zeno 義大利 Verona 維羅納" id="6237137862" latitude="45.442533" license="5" longitude="10.979011" nbComments="0" rank="32" tags="panasonic dmcgf1 italy verona 出遊 heritage church" title="Basilica di San Zeno" url_b="http://static.flickr.com/6162/6237137862_e5b7919e67_b.jpg" username="Richard, enjoy my life!" views="9" />
<photo  date_taken="2011-06-01 16:27:20" description="Basilica di San Zeno 義大利 Verona 維羅納" id="6236615735" latitude="45.442533" license="5" longitude="10.979011" nbComments="0" rank="33" tags="panasonic dmcgf1 italy verona 出遊 heritage church" title="Basilica di San Zeno" url_b="http://static.flickr.com/6096/6236615735_0430bc7ee8_b.jpg" username="Richard, enjoy my life!" views="2" />
<photo  date_taken="2011-06-01 16:28:51" description="Basilica di San Zeno 義大利 Verona 維羅納" id="6237141478" latitude="45.442533" license="5" longitude="10.979011" nbComments="0" rank="34" tags="panasonic dmcgf1 italy verona 出遊 heritage church" title="Basilica di San Zeno" url_b="http://static.flickr.com/6166/6237141478_6fdd57e8c8_b.jpg" username="Richard, enjoy my life!" views="16" />
<photo  date_taken="2011-06-01 16:24:47" description="Basilica di San Zeno 義大利 Verona 維羅納" id="6237135996" latitude="45.442533" license="5" longitude="10.979011" nbComments="0" rank="35" tags="panasonic dmcgf1 italy verona 出遊 heritage church" title="Basilica di San Zeno" url_b="http://static.flickr.com/6042/6237135996_cc79aaacfd_b.jpg" username="Richard, enjoy my life!" views="6" />
<photo  date_taken="2011-06-01 16:34:27" description="Basilica di San Zeno 義大利 Verona 維羅納" id="6237147978" latitude="45.442533" license="5" longitude="10.979011" nbComments="0" rank="36" tags="panasonic dmcgf1 italy verona 出遊 heritage church tower" title="Basilica di San Zeno" url_b="http://static.flickr.com/6114/6237147978_74a7c436da_b.jpg" username="Richard, enjoy my life!" views="9" />
<photo  date_taken="2011-06-01 16:32:51" description="Basilica di San Zeno 義大利 Verona 維羅納" id="6237145684" latitude="45.442533" license="5" longitude="10.979011" nbComments="0" rank="37" tags="panasonic dmcgf1 italy verona 出遊 heritage church" title="Basilica di San Zeno" url_b="http://static.flickr.com/6116/6237145684_f614652662_b.jpg" username="Richard, enjoy my life!" views="4" />
<photo  date_taken="2011-06-01 16:35:23" description="Basilica di San Zeno 義大利 Verona 維羅納" id="6236619691" latitude="45.442533" license="5" longitude="10.979011" nbComments="0" rank="38" tags="panasonic dmcgf1 italy verona 出遊 heritage church" title="Basilica di San Zeno" url_b="http://static.flickr.com/6221/6236619691_520effc164_b.jpg" username="Richard, enjoy my life!" views="3" />
<photo  date_taken="2010-02-13 17:39:49" description="Basilica di San Zeno a Verona" id="4356057514" latitude="45.44265" license="4" longitude="10.979257" nbComments="0" rank="39" tags="verona basilicadisanzeno sanzeno basilica" title="Basilica di San Zeno" url_b="http://static.flickr.com/2785/4356057514_c4157caa37_b.jpg" username="br1dotcom" views="89" />
<photo  date_taken="2010-02-13 17:39:43" description="Basilica di San Zeno a Verona" id="4356055710" latitude="45.44265" license="4" longitude="10.979257" nbComments="0" rank="40" tags="verona basilicadisanzeno sanzeno basilica" title="Basilica di San Zeno" url_b="http://static.flickr.com/2699/4356055710_e8c268623f_b.jpg" username="br1dotcom" views="105" />
<photo  date_taken="1995-01-01 00:00:00" description="" id="5336979580" latitude="45.442857" license="4" longitude="10.979177" nbComments="0" rank="41" tags="1995 verona veneto architectuur kerk europa italië" title="Basilica di San Zeno - Verona" url_b="http://static.flickr.com/5126/5336979580_2eac83c913_b.jpg" username="westher" views="24" />
<photo  date_taken="1995-01-01 00:00:00" description="" id="5336976778" latitude="45.442488" license="4" longitude="10.978807" nbComments="0" rank="42" tags="1995 verona veneto architectuur kerk europa italië" title="Basilica di San Zeno - Verona {1995}" url_b="http://static.flickr.com/5127/5336976778_ff35d1d29d_b.jpg" username="westher" views="40" />
<photo  date_taken="1995-01-01 00:00:00" description="" id="5336951864" latitude="45.442865" license="4" longitude="10.979177" nbComments="0" rank="43" tags="1995 verona veneto architectuur kerk europa italië" title="Basilica di San Zeno - Verona" url_b="http://static.flickr.com/5050/5336951864_b9cca08237_b.jpg" username="westher" views="13" />
<photo  date_taken="2010-02-13 17:34:17" description="Basilica di San Zeno a Verona" id="4355291847" latitude="45.442925" license="4" longitude="10.979118" nbComments="0" rank="44" tags="verona basilicadisanzeno sanzeno basilica" title="Basilica di San Zeno" url_b="http://static.flickr.com/4048/4355291847_f9509e2cb7_b.jpg" username="br1dotcom" views="43" />
<photo  date_taken="2011-06-01 16:19:30" description="Basilica di San Zeno 義大利 Verona 維羅納" id="6236610155" latitude="45.442217" license="5" longitude="10.97841" nbComments="0" rank="45" tags="panasonic dmcgf1 italy verona 出遊 heritage church tower" title="Basilica di San Zeno" url_b="http://static.flickr.com/6115/6236610155_fcbcfbe12d_b.jpg" username="Richard, enjoy my life!" views="12" />
<photo  date_taken="2008-10-02 15:07:04" description="Verona Sep 2008" id="3523592746" latitude="45.442074" license="4" longitude="10.978163" nbComments="0" rank="46" tags="verona basilicadisanzeno" title="Basilica di San Zeno" url_b="http://static.flickr.com/3409/3523592746_a9852b00bd_b.jpg" username="asw909" views="73" />
<photo  date_taken="2009-09-23 17:03:31" description="" id="3970020318" latitude="45.44055" license="4" longitude="10.982294" nbComments="2" rank="47" tags="basilicadisanzeno canoneos5dmk1 ef50mmf14usm italy veneto verona" title="basilica di san zeno" url_b="http://static.flickr.com/2624/3970020318_f1a3a8bdbc_b.jpg" username="slowpoke748" views="43" />
</photos>
